{"ticker": "NDX", "timestamp": "2026-07-16T20:00:00", "frequency": "eod", "spot_price": 29030.42, "totals": {"net_gex": -595697.9724416763, "abs_gex": 30426658.31532466, "net_dex": 10586303399.512531, "abs_dex": 91424044373.67761, "net_oi": 3376.0, "abs_oi": 121954.0}, "expirations": [{"expiration_date": "2026-07-17", "dte": 1, "net_gex": -1058517.0829785343, "abs_gex": 12158436.822227675, "net_dex": -2206981842.9753776, "abs_dex": 10579502082.446547, "net_oi": 161.0, "abs_oi": 28473.0, "gex_normalized": -33.152012497731285, "dex_normalized": -10.47608137436369, "oi_normalized": 1.5350877192982455, "gex_change_1h": null, "dex_change_1h": null, "gex_change_1d": -5331851.238543925, "dex_change_1d": -6163888033.13777, "call_resistance": null, "put_support": null, "hvl": null, "implied_expected_move": null}, {"expiration_date": "2026-08-21", "dte": 36, "net_gex": -466021.5402122926, "abs_gex": 4418454.252159981, "net_dex": -2270781039.418062, "abs_dex": 9428033418.071846, "net_oi": 440.0, "abs_oi": 15434.0, "gex_normalized": -14.595467729114779, "dex_normalized": -10.778922820785155, "oi_normalized": 4.195270785659801, "gex_change_1h": null, "dex_change_1h": null, "gex_change_1d": -560306.433457641, "dex_change_1d": -1988578172.661051, "call_resistance": null, "put_support": null, "hvl": null, "implied_expected_move": null}, {"expiration_date": "2026-09-18", "dte": 64, "net_gex": -178518.30563763602, "abs_gex": 6234587.148943864, "net_dex": 1150232989.3898346, "abs_dex": 22899523375.901752, "net_oi": -613.0, "abs_oi": 23553.0, "gex_normalized": -5.591068103425912, "dex_normalized": 5.459915510714036, "oi_normalized": -5.844774980930588, "gex_change_1h": null, "dex_change_1h": null, "gex_change_1d": -265824.23056830367, "dex_change_1d": -3169227191.8741465, "call_resistance": null, "put_support": null, "hvl": null, "implied_expected_move": null}, {"expiration_date": "2026-10-16", "dte": 92, "net_gex": -54289.85372635512, "abs_gex": 582864.7739631884, "net_dex": -186561207.12768123, "abs_dex": 2284611227.25568, "net_oi": 498.0, "abs_oi": 3808.0, "gex_normalized": -1.700320134816971, "dex_normalized": -0.8855670441466847, "oi_normalized": 4.748283752860412, "gex_change_1h": null, "dex_change_1h": null, "gex_change_1d": -45677.894703917555, "dex_change_1d": -321613068.82649386, "call_resistance": null, "put_support": null, "hvl": null, "implied_expected_move": null}, {"expiration_date": "2026-11-20", "dte": 127, "net_gex": -97786.80602729997, "abs_gex": 236024.6429761198, "net_dex": -328539777.5200154, "abs_dex": 1042985345.3579209, "net_oi": -368.0, "abs_oi": 1792.0, "gex_normalized": -3.062614168122986, "dex_normalized": -1.5595096330175937, "oi_normalized": -3.508771929824561, "gex_change_1h": null, "dex_change_1h": null, "gex_change_1d": -20622.492268552975, "dex_change_1d": -126880010.92824179, "call_resistance": null, "put_support": null, "hvl": null, "implied_expected_move": null}, {"expiration_date": "2026-12-18", "dte": 155, "net_gex": 115407.04437419846, "abs_gex": 3206875.470418877, "net_dex": 4094408295.8945575, "abs_dex": 19475179931.6711, "net_oi": -1295.0, "abs_oi": 24567.0, "gex_normalized": 3.6144676726934257, "dex_normalized": 19.435300124551, "oi_normalized": -12.347444698703281, "gex_change_1h": null, "dex_change_1h": null, "gex_change_1d": -80864.60959165743, "dex_change_1d": -1247288801.1439977, "call_resistance": null, "put_support": null, "hvl": null, "implied_expected_move": null}, {"expiration_date": "2027-01-15", "dte": 183, "net_gex": 909065.1796563225, "abs_gex": 1936341.2301710253, "net_dex": 7358154571.17233, "abs_dex": 12692948707.476202, "net_oi": 4437.0, "abs_oi": 10691.0, "gex_normalized": 28.471283724978765, "dex_normalized": 34.927621311476045, "oi_normalized": 42.30549199084668, "gex_change_1h": null, "dex_change_1h": null, "gex_change_1d": -16993.979256329127, "dex_change_1d": -1040397428.1866236, "call_resistance": null, "put_support": null, "hvl": null, "implied_expected_move": null}, {"expiration_date": "2027-02-19", "dte": 218, "net_gex": -26051.815178139197, "abs_gex": 71134.62824949871, "net_dex": -155863215.9922008, "abs_dex": 425416653.0801316, "net_oi": -143.0, "abs_oi": 437.0, "gex_normalized": -0.8159245762420733, "dex_normalized": -0.7398500985413572, "oi_normalized": -1.3634630053394354, "gex_change_1h": null, "dex_change_1h": null, "gex_change_1d": -2569.684802855707, "dex_change_1d": -31641695.845420986, "call_resistance": null, "put_support": null, "hvl": null, "implied_expected_move": null}, {"expiration_date": "2027-03-19", "dte": 246, "net_gex": 256070.965767795, "abs_gex": 779445.4114342587, "net_dex": 1915356994.1380558, "abs_dex": 5217714852.491871, "net_oi": 1174.0, "abs_oi": 5144.0, "gex_normalized": 8.01996301613983, "dex_normalized": 9.091799189655033, "oi_normalized": 11.193745232646835, "gex_change_1h": null, "dex_change_1h": null, "gex_change_1d": -3166.8970248888363, "dex_change_1d": -312568617.3202629, "call_resistance": null, "put_support": null, "hvl": null, "implied_expected_move": null}, {"expiration_date": "2027-04-16", "dte": 274, "net_gex": 11842.21642634434, "abs_gex": 26002.289046707818, "net_dex": 62905243.59486902, "abs_dex": 157257325.9740384, "net_oi": 96.0, "abs_oi": 262.0, "gex_normalized": 0.37088991125424065, "dex_normalized": 0.29859803915993083, "oi_normalized": 0.9153318077803204, "gex_change_1h": null, "dex_change_1h": null, "gex_change_1d": -997.9921002967858, "dex_change_1d": -13745227.923737943, "call_resistance": null, "put_support": null, "hvl": null, "implied_expected_move": null}, {"expiration_date": "2027-05-21", "dte": 309, "net_gex": -2748.4097850596445, "abs_gex": 3354.3358073475483, "net_dex": -22471386.298169445, "abs_dex": 25620390.009176925, "net_oi": -19.0, "abs_oi": 23.0, "gex_normalized": -0.08607826648087456, "dex_normalized": -0.10666697245547332, "oi_normalized": -0.18115942028985507, "gex_change_1h": null, "dex_change_1h": null, "gex_change_1d": -152.7422385285049, "dex_change_1d": -1509371.572440263, "call_resistance": null, "put_support": null, "hvl": null, "implied_expected_move": null}, {"expiration_date": "2027-06-17", "dte": 336, "net_gex": 49.95927353401197, "abs_gex": 513920.98523482605, "net_dex": -20331859.076319866, "abs_dex": 3670649979.108717, "net_oi": -339.0, "abs_oi": 4153.0, "gex_normalized": 0.0015646894010596974, "dex_normalized": -0.09651108406422816, "oi_normalized": -3.232265446224256, "gex_change_1h": null, "dex_change_1h": null, "gex_change_1d": -35456.86305858456, "dex_change_1d": -401792967.43470526, "call_resistance": null, "put_support": null, "hvl": null, "implied_expected_move": null}, {"expiration_date": "2027-09-17", "dte": 428, "net_gex": -5326.008546747046, "abs_gex": 13968.307963047491, "net_dex": -48750102.174950175, "abs_dex": 119385839.87602624, "net_oi": -64.0, "abs_oi": 126.0, "gex_normalized": -0.16680685153227925, "dex_normalized": -0.231406542386774, "oi_normalized": -0.6102212051868803, "gex_change_1h": null, "dex_change_1h": null, "gex_change_1d": -296.9523156545056, "dex_change_1d": -1327380.7185013816, "call_resistance": null, "put_support": null, "hvl": null, "implied_expected_move": null}, {"expiration_date": "2027-12-17", "dte": 519, "net_gex": -806.7380119889236, "abs_gex": 200975.46297765197, "net_dex": 463406698.97354436, "abs_dex": 2091467060.255532, "net_oi": -561.0, "abs_oi": 2483.0, "gex_normalized": -0.02526646861531478, "dex_normalized": 2.199694711274646, "oi_normalized": -5.348970251716247, "gex_change_1h": null, "dex_change_1h": null, "gex_change_1d": -3422.31727438624, "dex_change_1d": -99958784.3081783, "call_resistance": null, "put_support": null, "hvl": null, "implied_expected_move": null}, {"expiration_date": "2028-12-15", "dte": 883, "net_gex": -4242.193153511443, "abs_gex": 22124.727541032305, "net_dex": 129051803.5073699, "abs_dex": 395142947.8406755, "net_oi": -154.0, "abs_oi": 432.0, "gex_normalized": -0.13286251370385624, "dex_normalized": 0.6125819291874817, "oi_normalized": -1.4683447749809306, "gex_change_1h": null, "dex_change_1h": null, "gex_change_1d": -427.7288793073112, "dex_change_1d": -14756050.330668211, "call_resistance": null, "put_support": null, "hvl": null, "implied_expected_move": null}, {"expiration_date": "2029-12-21", "dte": 1254, "net_gex": 6175.415317693701, "abs_gex": 22147.826209557694, "net_dex": 653067233.4247472, "abs_dex": 918605236.8604007, "net_oi": 126.0, "abs_oi": 576.0, "gex_normalized": 0.19340967574636153, "dex_normalized": 3.09997361422087, "oi_normalized": 1.2013729977116705, "gex_change_1h": null, "dex_change_1h": null, "gex_change_1d": 496.6686579521156, "dex_change_1d": -21502363.18811202, "call_resistance": null, "put_support": null, "hvl": null, "implied_expected_move": null}]}