{
  "success": true,
  "data": {
    "date": "2026-05-22",
    "resource": {
      "ticker": "CLQ2026",
      "image_url": "",
      "data": {
        "Call Resistance": 115,
        "Call Resistance 0DTE": 104,
        "High Vol Level": 94.5,
        "Put Support": 75,
        "Put Support 0DTE": 93,
        "1D Max.": 97.16,
        "1D Min.": 89.02,
        "Distance to HVL %": "1.51%",
        "Implied Vol 30D": 69.39,
        "Total GEX": "213.26M",
        "Net GEX": "12.28M",
        "Expiring GEX": "-0.00M",
        "Put/Call GEX": 0.89,
        "Total DEX": "7.45B",
        "Net DEX": "2.67B",
        "Put/Call DEX": 0.47
      },
      "text_data": "",
      "table_data": [],
      "date": "2026-05-22",
      "run_id": null,
      "run_timestamp": null,
      "previous_run_id": null,
      "next_run_id": null,
      "quin_url_template": null
    }
  }
}