{
 "span": [
  "2021-06-17",
  "2026-07-02"
 ],
 "years": 5.0,
 "daily": {
  "n": 37,
  "tot": 5722,
  "pf": 2.15,
  "win": 57,
  "openDD": 945
 },
 "fourh": {
  "n": 74,
  "tot": 6121,
  "pf": 2.38,
  "win": 77,
  "openDD": 1454
 },
 "combo": {
  "n": 111,
  "tot": 11844,
  "ann": 2351,
  "pf": 2.26,
  "win": 70,
  "openDD": 1662,
  "peakC": 3
 },
 "peryear": {
  "2021": [
   7,
   890
  ],
  "2022": [
   14,
   -535
  ],
  "2023": [
   24,
   1506
  ],
  "2024": [
   32,
   3989
  ],
  "2025": [
   23,
   2582
  ],
  "2026": [
   11,
   3411
  ]
 },
 "equity": [
  [
   "2021-09-15",
   -224
  ],
  [
   "2021-11-12",
   -189
  ],
  [
   "2021-11-28",
   -36
  ],
  [
   "2021-11-29",
   334
  ],
  [
   "2021-11-29",
   682
  ],
  [
   "2021-11-30",
   700
  ],
  [
   "2021-12-15",
   890
  ],
  [
   "2022-01-06",
   580
  ],
  [
   "2022-01-10",
   390
  ],
  [
   "2022-01-19",
   80
  ],
  [
   "2022-04-04",
   324
  ],
  [
   "2022-04-07",
   498
  ],
  [
   "2022-04-13",
   501
  ],
  [
   "2022-07-27",
   718
  ],
  [
   "2022-08-24",
   292
  ],
  [
   "2022-08-25",
   822
  ],
  [
   "2022-08-28",
   512
  ],
  [
   "2022-09-01",
   -236
  ],
  [
   "2022-11-30",
   334
  ],
  [
   "2022-12-08",
   410
  ],
  [
   "2022-12-21",
   355
  ],
  [
   "2023-01-20",
   264
  ],
  [
   "2023-01-20",
   600
  ],
  [
   "2023-02-13",
   844
  ],
  [
   "2023-02-23",
   429
  ],
  [
   "2023-02-24",
   119
  ],
  [
   "2023-04-27",
   159
  ],
  [
   "2023-04-27",
   529
  ],
  [
   "2023-05-05",
   631
  ],
  [
   "2023-05-05",
   1001
  ],
  [
   "2023-05-15",
   1155
  ],
  [
   "2023-05-25",
   1110
  ],
  [
   "2023-05-26",
   1480
  ],
  [
   "2023-06-22",
   1516
  ],
  [
   "2023-06-27",
   1608
  ],
  [
   "2023-06-27",
   1922
  ],
  [
   "2023-08-04",
   1996
  ],
  [
   "2023-08-04",
   1686
  ],
  [
   "2023-08-07",
   1871
  ],
  [
   "2023-08-11",
   1849
  ],
  [
   "2023-08-16",
   1539
  ],
  [
   "2023-09-08",
   1360
  ],
  [
   "2023-11-30",
   1461
  ],
  [
   "2023-12-07",
   1620
  ],
  [
   "2023-12-21",
   1861
  ],
  [
   "2024-01-05",
   1551
  ],
  [
   "2024-01-08",
   1664
  ],
  [
   "2024-01-18",
   1882
  ],
  [
   "2024-02-01",
   2239
  ],
  [
   "2024-02-01",
   2595
  ],
  [
   "2024-02-14",
   2818
  ],
  [
   "2024-02-21",
   2881
  ],
  [
   "2024-02-29",
   2971
  ],
  [
   "2024-03-18",
   3224
  ],
  [
   "2024-03-27",
   3419
  ],
  [
   "2024-04-05",
   4159
  ],
  [
   "2024-04-05",
   4502
  ],
  [
   "2024-04-11",
   4685
  ],
  [
   "2024-04-11",
   5180
  ],
  [
   "2024-04-15",
   4870
  ],
  [
   "2024-05-30",
   4560
  ],
  [
   "2024-05-31",
   4642
  ],
  [
   "2024-06-25",
   4725
  ],
  [
   "2024-07-22",
   4518
  ],
  [
   "2024-07-23",
   4888
  ],
  [
   "2024-09-06",
   4578
  ],
  [
   "2024-09-09",
   4174
  ],
  [
   "2024-10-04",
   4396
  ],
  [
   "2024-10-24",
   4475
  ],
  [
   "2024-11-05",
   4689
  ],
  [
   "2024-11-05",
   5429
  ],
  [
   "2024-11-19",
   5119
  ],
  [
   "2024-11-19",
   4934
  ],
  [
   "2024-12-11",
   5118
  ],
  [
   "2024-12-16",
   5340
  ],
  [
   "2024-12-16",
   5480
  ],
  [
   "2024-12-19",
   5850
  ],
  [
   "2025-02-24",
   5540
  ],
  [
   "2025-02-28",
   4980
  ],
  [
   "2025-05-23",
   4670
  ],
  [
   "2025-05-26",
   4855
  ],
  [
   "2025-05-30",
   5109
  ],
  [
   "2025-06-20",
   5479
  ],
  [
   "2025-06-20",
   5728
  ],
  [
   "2025-07-16",
   5841
  ],
  [
   "2025-08-04",
   6581
  ],
  [
   "2025-08-04",
   6482
  ],
  [
   "2025-08-22",
   6564
  ],
  [
   "2025-09-03",
   6900
  ],
  [
   "2025-09-26",
   6922
  ],
  [
   "2025-10-10",
   6612
  ],
  [
   "2025-10-13",
   6869
  ],
  [
   "2025-11-03",
   7035
  ],
  [
   "2025-11-04",
   6725
  ],
  [
   "2025-11-05",
   6929
  ],
  [
   "2025-11-07",
   6938
  ],
  [
   "2025-11-19",
   7678
  ],
  [
   "2025-12-18",
   8418
  ],
  [
   "2025-12-18",
   8268
  ],
  [
   "2026-01-05",
   8432
  ],
  [
   "2026-01-15",
   8798
  ],
  [
   "2026-01-21",
   9538
  ],
  [
   "2026-04-30",
   9829
  ],
  [
   "2026-05-20",
   10569
  ],
  [
   "2026-05-20",
   10852
  ],
  [
   "2026-06-04",
   10981
  ],
  [
   "2026-06-08",
   11721
  ],
  [
   "2026-06-09",
   11295
  ],
  [
   "2026-06-11",
   11966
  ],
  [
   "2026-06-25",
   11656
  ],
  [
   "2026-06-29",
   11844
  ]
 ],
 "sizing": [
  {
   "k": 3,
   "ann": 7053,
   "pct": 7,
   "dd": 4986,
   "ddpct": 5,
   "margin": 22050,
   "mpct": 22
  },
  {
   "k": 4,
   "ann": 9404,
   "pct": 9,
   "dd": 6648,
   "ddpct": 7,
   "margin": 29400,
   "mpct": 29
  },
  {
   "k": 5,
   "ann": 11755,
   "pct": 12,
   "dd": 8310,
   "ddpct": 8,
   "margin": 36750,
   "mpct": 37
  },
  {
   "k": 6,
   "ann": 14106,
   "pct": 14,
   "dd": 9972,
   "ddpct": 10,
   "margin": 44100,
   "mpct": 44
  },
  {
   "k": 8,
   "ann": 18808,
   "pct": 19,
   "dd": 13296,
   "ddpct": 13,
   "margin": 58800,
   "mpct": 59
  }
 ],
 "peryear_full": {
  "2021": [
   7,
   86,
   4.98,
   890
  ],
  "2022": [
   14,
   50,
   0.77,
   -535
  ],
  "2023": [
   24,
   67,
   1.9,
   1506
  ],
  "2024": [
   32,
   75,
   2.7,
   3989
  ],
  "2025": [
   23,
   70,
   2.26,
   2582
  ],
  "2026": [
   11,
   82,
   5.63,
   3411
  ]
 },
 "acct_min_base1": 9012
}